{"stats":{"minecraft:picked_up":{"minecraft:cooked_cod":5,"minecraft:cobblestone":1},"minecraft:used":{"minecraft:cobblestone":1,"minecraft:cooked_cod":3},"minecraft:custom":{"minecraft:open_barrel":3,"minecraft:time_since_rest":10983,"minecraft:open_chest":6,"minecraft:play_one_minute":13088,"minecraft:crouch_one_cm":2328,"minecraft:interact_with_furnace":3,"minecraft:sprint_one_cm":48671,"minecraft:damage_taken":40,"minecraft:walk_one_cm":35742,"minecraft:sneak_time":548,"minecraft:bell_ring":3,"minecraft:drop":2,"minecraft:jump":298,"minecraft:damage_dealt":10,"minecraft:leave_game":1,"minecraft:time_since_death":13088,"minecraft:walk_on_water_one_cm":217,"minecraft:sleep_in_bed":1,"minecraft:fall_one_cm":6931,"minecraft:interact_with_crafting_table":1,"minecraft:tune_noteblock":7,"minecraft:fly_one_cm":63378},"minecraft:dropped":{"minecraft:cooked_cod":2}},"DataVersion":2578}